Peeves/Profiler.py
Peeves/TestUtils.py
Peeves/Timer.py
Peeves/__init__.py
Peeves/run_tests.py
Peeves/Doc/DocWalker.py
Peeves/Doc/DocsBuilder.py
Peeves/Doc/ExamplesParser.py
Peeves/Doc/MarkdownTemplates.py
Peeves/Doc/ObjectWalker.py
Peeves/Doc/TemplateEngine.py
Peeves/Doc/Writers.py
Peeves/Doc/__init__.py
Peeves/Doc/HTML/Bootstrap.py
Peeves/Doc/HTML/BootstrapEnums.py
Peeves/Doc/HTML/Enums.py
Peeves/Doc/HTML/HTML.py
Peeves/Doc/HTML/__init__.py
mccoygroup_peeves-0.1.0.dist-info/LICENSE.txt
mccoygroup_peeves-0.1.0.dist-info/METADATA
mccoygroup_peeves-0.1.0.dist-info/WHEEL
mccoygroup_peeves-0.1.0.dist-info/top_level.txt
mccoygroup_peeves-0.1.0.dist-info/RECORD
