Metadata-Version: 2.1
Name: mccoygroup-peeves
Version: 0.1.0
Summary: UNKNOWN
Home-page: UNKNOWN
Author: Mark Boyer
Author-email: b3m2a1@uw.edu
License: MIT
Platform: UNKNOWN
